MANIFEST.in
README.rst
setup.cfg
setup.py
blo/__init__.py
blo/blog.py
blo/content_aggregator.py
blo/default.json
blo/draft_templates.json
blo/page_generator.py
blo/tests.sh
blo.egg-info/PKG-INFO
blo.egg-info/SOURCES.txt
blo.egg-info/dependency_links.txt
blo.egg-info/entry_points.txt
blo.egg-info/requires.txt
blo.egg-info/top_level.txt
blo/templates/base.html
blo/templates/list.html
blo/templates/page.html
blo/templates/post.html
blo/templates/stat.html
blo/tests/__init__.py
blo/tests/test_blog.py