Metadata-Version: 1.1
Name: blo
Version: 0.8
Summary: Blo - a simple static blog generator
Home-page: https://github.com/savuir/blo
Author: Yann Savuir
Author-email: savuir@gmail.com
License: BSD-3-clause
Download-URL: https://github.com/savuir/blo/tarball/0.1
Keywords: blogging,blog,static blog generator
Platform: UNKNOWN
